{
    "scene_type": "distance_barrier_rb_problem",
    "solver": "ipc_solver",
    "timestep": 0.01,
    "max_time": 10,
    "distance_barrier_constraint": {
        "barrier_type": "ipc",
        "initial_barrier_activation_distance": 1e-2
    },
    "ipc_solver": {
        "#convergence_criteria": "energy",
        "#velocity_conv_tol": 1e-5
    },
    "rigid_body_problem": {
        "coefficient_restitution": -1,
        "coefficient_friction": 1e-2,
        "gravity": [0, -9.8, 0],
        "rigid_bodies": [{
            "mesh": "cube-symmetric.obj",
            "position": [-3, 2.5, 0],
            "rotation": [0, 0, 0]
        }, {
            "mesh": "plane-symmetric.obj",
            "is_dof_fixed": true,
            "position": [5, -1, 0],
            "scale": [2, 1, 2],
            "rotation": [0, 0, -15]
        }]
    }
}