{
    "scene_type": "distance_barrier_rb_problem",
    "timestep_size": 0.01,
    "max_time": 2.5,
    "rigid_body_problem": {
        "coefficient_restitution": -1,
        "gravity": [0, -9.8, 0],
        "rigid_bodies": [{
                "mesh": "cube.obj",
                "position": [0, 0.05, 0],
                "rotation": [0, 0, 0],
                "linear_velocity": [0, 0, 0],
                "angular_velocity": [0, 0, 0]
            },
            {
                "mesh": "erleben/cliff.obj",
                "is_dof_fixed": [true, true, true, true, true, true],
                "position": [0, -1.0, 0]
            }
        ]
    }
}