{"scene_type":"distance_barrier_rb_problem","solver":"ipc_solver","timestep":0.01,"max_time":20.0,"friction_constraints":{"iterations":1},"rigid_body_problem":{"coefficient_restitution":-1,"coefficient_friction":0.5,"gravity":[0,-9.8,0],"rigid_bodies":[{"mesh":"plane.obj","position":[0,0,0],"dimensions":[226.58266542364842,0.0,100.0],"is_dof_fixed":true},{"mesh":"arch/num_stones=951/stone-01.obj"},{"mesh":"arch/num_stones=951/stone-02.obj"},{"mesh":"arch/num_stones=951/stone-03.obj"},{"mesh":"arch/num_stones=951/stone-04.obj"},{"mesh":"arch/num_stones=951/stone-05.obj"},{"mesh":"arch/num_stones=951/stone-06.obj"},{"mesh":"arch/num_stones=951/stone-07.obj"},{"mesh":"arch/num_stones=951/stone-08.obj"},{"mesh":"arch/num_stones=951/stone-09.obj"},{"mesh":"arch/num_stones=951/stone-10.obj"},{"mesh":"arch/num_stones=951/stone-11.obj"},{"mesh":"arch/num_stones=951/stone-12.obj"},{"mesh":"arch/num_stones=951/stone-13.obj"},{"mesh":"arch/num_stones=951/stone-14.obj"},{"mesh":"arch/num_stones=951/stone-15.obj"},{"mesh":"arch/num_stones=951/stone-16.obj"},{"mesh":"arch/num_stones=951/stone-17.obj"},{"mesh":"arch/num_stones=951/stone-18.obj"},{"mesh":"arch/num_stones=951/stone-19.obj"},{"mesh":"arch/num_stones=951/stone-20.obj"},{"mesh":"arch/num_stones=951/stone-21.obj"},{"mesh":"arch/num_stones=951/stone-22.obj"},{"mesh":"arch/num_stones=951/stone-23.obj"},{"mesh":"arch/num_stones=951/stone-24.obj"},{"mesh":"arch/num_stones=951/stone-25.obj"},{"mesh":"arch/num_stones=951/stone-26.obj"},{"mesh":"arch/num_stones=951/stone-27.obj"},{"mesh":"arch/num_stones=951/stone-28.obj"},{"mesh":"arch/num_stones=951/stone-29.obj"},{"mesh":"arch/num_stones=951/stone-30.obj"},{"mesh":"arch/num_stones=951/stone-31.obj"},{"mesh":"arch/num_stones=951/stone-32.obj"},{"mesh":"arch/num_stones=951/stone-33.obj"},{"mesh":"arch/num_stones=951/stone-34.obj"},{"mesh":"arch/num_stones=951/stone-35.obj"},{"mesh":"arch/num_stones=951/stone-36.obj"},{"mesh":"arch/num_stones=951/stone-37.obj"},{"mesh":"arch/num_stones=951/stone-38.obj"},{"mesh":"arch/num_stones=951/stone-39.obj"},{"mesh":"arch/num_stones=951/stone-40.obj"},{"mesh":"arch/num_stones=951/stone-41.obj"},{"mesh":"arch/num_stones=951/stone-42.obj"},{"mesh":"arch/num_stones=951/stone-43.obj"},{"mesh":"arch/num_stones=951/stone-44.obj"},{"mesh":"arch/num_stones=951/stone-45.obj"},{"mesh":"arch/num_stones=951/stone-46.obj"},{"mesh":"arch/num_stones=951/stone-47.obj"},{"mesh":"arch/num_stones=951/stone-48.obj"},{"mesh":"arch/num_stones=951/stone-49.obj"},{"mesh":"arch/num_stones=951/stone-50.obj"},{"mesh":"arch/num_stones=951/stone-51.obj"},{"mesh":"arch/num_stones=951/stone-52.obj"},{"mesh":"arch/num_stones=951/stone-53.obj"},{"mesh":"arch/num_stones=951/stone-54.obj"},{"mesh":"arch/num_stones=951/stone-55.obj"},{"mesh":"arch/num_stones=951/stone-56.obj"},{"mesh":"arch/num_stones=951/stone-57.obj"},{"mesh":"arch/num_stones=951/stone-58.obj"},{"mesh":"arch/num_stones=951/stone-59.obj"},{"mesh":"arch/num_stones=951/stone-60.obj"},{"mesh":"arch/num_stones=951/stone-61.obj"},{"mesh":"arch/num_stones=951/stone-62.obj"},{"mesh":"arch/num_stones=951/stone-63.obj"},{"mesh":"arch/num_stones=951/stone-64.obj"},{"mesh":"arch/num_stones=951/stone-65.obj"},{"mesh":"arch/num_stones=951/stone-66.obj"},{"mesh":"arch/num_stones=951/stone-67.obj"},{"mesh":"arch/num_stones=951/stone-68.obj"},{"mesh":"arch/num_stones=951/stone-69.obj"},{"mesh":"arch/num_stones=951/stone-70.obj"},{"mesh":"arch/num_stones=951/stone-71.obj"},{"mesh":"arch/num_stones=951/stone-72.obj"},{"mesh":"arch/num_stones=951/stone-73.obj"},{"mesh":"arch/num_stones=951/stone-74.obj"},{"mesh":"arch/num_stones=951/stone-75.obj"},{"mesh":"arch/num_stones=951/stone-76.obj"},{"mesh":"arch/num_stones=951/stone-77.obj"},{"mesh":"arch/num_stones=951/stone-78.obj"},{"mesh":"arch/num_stones=951/stone-79.obj"},{"mesh":"arch/num_stones=951/stone-80.obj"},{"mesh":"arch/num_stones=951/stone-81.obj"},{"mesh":"arch/num_stones=951/stone-82.obj"},{"mesh":"arch/num_stones=951/stone-83.obj"},{"mesh":"arch/num_stones=951/stone-84.obj"},{"mesh":"arch/num_stones=951/stone-85.obj"},{"mesh":"arch/num_stones=951/stone-86.obj"},{"mesh":"arch/num_stones=951/stone-87.obj"},{"mesh":"arch/num_stones=951/stone-88.obj"},{"mesh":"arch/num_stones=951/stone-89.obj"},{"mesh":"arch/num_stones=951/stone-90.obj"},{"mesh":"arch/num_stones=951/stone-91.obj"},{"mesh":"arch/num_stones=951/stone-92.obj"},{"mesh":"arch/num_stones=951/stone-93.obj"},{"mesh":"arch/num_stones=951/stone-94.obj"},{"mesh":"arch/num_stones=951/stone-95.obj"},{"mesh":"arch/num_stones=951/stone-96.obj"},{"mesh":"arch/num_stones=951/stone-97.obj"},{"mesh":"arch/num_stones=951/stone-98.obj"},{"mesh":"arch/num_stones=951/stone-99.obj"},{"mesh":"arch/num_stones=951/stone-100.obj"},{"mesh":"arch/num_stones=951/stone-101.obj"},{"mesh":"arch/num_stones=951/stone-102.obj"},{"mesh":"arch/num_stones=951/stone-103.obj"},{"mesh":"arch/num_stones=951/stone-104.obj"},{"mesh":"arch/num_stones=951/stone-105.obj"},{"mesh":"arch/num_stones=951/stone-106.obj"},{"mesh":"arch/num_stones=951/stone-107.obj"},{"mesh":"arch/num_stones=951/stone-108.obj"},{"mesh":"arch/num_stones=951/stone-109.obj"},{"mesh":"arch/num_stones=951/stone-110.obj"},{"mesh":"arch/num_stones=951/stone-111.obj"},{"mesh":"arch/num_stones=951/stone-112.obj"},{"mesh":"arch/num_stones=951/stone-113.obj"},{"mesh":"arch/num_stones=951/stone-114.obj"},{"mesh":"arch/num_stones=951/stone-115.obj"},{"mesh":"arch/num_stones=951/stone-116.obj"},{"mesh":"arch/num_stones=951/stone-117.obj"},{"mesh":"arch/num_stones=951/stone-118.obj"},{"mesh":"arch/num_stones=951/stone-119.obj"},{"mesh":"arch/num_stones=951/stone-120.obj"},{"mesh":"arch/num_stones=951/stone-121.obj"},{"mesh":"arch/num_stones=951/stone-122.obj"},{"mesh":"arch/num_stones=951/stone-123.obj"},{"mesh":"arch/num_stones=951/stone-124.obj"},{"mesh":"arch/num_stones=951/stone-125.obj"},{"mesh":"arch/num_stones=951/stone-126.obj"},{"mesh":"arch/num_stones=951/stone-127.obj"},{"mesh":"arch/num_stones=951/stone-128.obj"},{"mesh":"arch/num_stones=951/stone-129.obj"},{"mesh":"arch/num_stones=951/stone-130.obj"},{"mesh":"arch/num_stones=951/stone-131.obj"},{"mesh":"arch/num_stones=951/stone-132.obj"},{"mesh":"arch/num_stones=951/stone-133.obj"},{"mesh":"arch/num_stones=951/stone-134.obj"},{"mesh":"arch/num_stones=951/stone-135.obj"},{"mesh":"arch/num_stones=951/stone-136.obj"},{"mesh":"arch/num_stones=951/stone-137.obj"},{"mesh":"arch/num_stones=951/stone-138.obj"},{"mesh":"arch/num_stones=951/stone-139.obj"},{"mesh":"arch/num_stones=951/stone-140.obj"},{"mesh":"arch/num_stones=951/stone-141.obj"},{"mesh":"arch/num_stones=951/stone-142.obj"},{"mesh":"arch/num_stones=951/stone-143.obj"},{"mesh":"arch/num_stones=951/stone-144.obj"},{"mesh":"arch/num_stones=951/stone-145.obj"},{"mesh":"arch/num_stones=951/stone-146.obj"},{"mesh":"arch/num_stones=951/stone-147.obj"},{"mesh":"arch/num_stones=951/stone-148.obj"},{"mesh":"arch/num_stones=951/stone-149.obj"},{"mesh":"arch/num_stones=951/stone-150.obj"},{"mesh":"arch/num_stones=951/stone-151.obj"},{"mesh":"arch/num_stones=951/stone-152.obj"},{"mesh":"arch/num_stones=951/stone-153.obj"},{"mesh":"arch/num_stones=951/stone-154.obj"},{"mesh":"arch/num_stones=951/stone-155.obj"},{"mesh":"arch/num_stones=951/stone-156.obj"},{"mesh":"arch/num_stones=951/stone-157.obj"},{"mesh":"arch/num_stones=951/stone-158.obj"},{"mesh":"arch/num_stones=951/stone-159.obj"},{"mesh":"arch/num_stones=951/stone-160.obj"},{"mesh":"arch/num_stones=951/stone-161.obj"},{"mesh":"arch/num_stones=951/stone-162.obj"},{"mesh":"arch/num_stones=951/stone-163.obj"},{"mesh":"arch/num_stones=951/stone-164.obj"},{"mesh":"arch/num_stones=951/stone-165.obj"},{"mesh":"arch/num_stones=951/stone-166.obj"},{"mesh":"arch/num_stones=951/stone-167.obj"},{"mesh":"arch/num_stones=951/stone-168.obj"},{"mesh":"arch/num_stones=951/stone-169.obj"},{"mesh":"arch/num_stones=951/stone-170.obj"},{"mesh":"arch/num_stones=951/stone-171.obj"},{"mesh":"arch/num_stones=951/stone-172.obj"},{"mesh":"arch/num_stones=951/stone-173.obj"},{"mesh":"arch/num_stones=951/stone-174.obj"},{"mesh":"arch/num_stones=951/stone-175.obj"},{"mesh":"arch/num_stones=951/stone-176.obj"},{"mesh":"arch/num_stones=951/stone-177.obj"},{"mesh":"arch/num_stones=951/stone-178.obj"},{"mesh":"arch/num_stones=951/stone-179.obj"},{"mesh":"arch/num_stones=951/stone-180.obj"},{"mesh":"arch/num_stones=951/stone-181.obj"},{"mesh":"arch/num_stones=951/stone-182.obj"},{"mesh":"arch/num_stones=951/stone-183.obj"},{"mesh":"arch/num_stones=951/stone-184.obj"},{"mesh":"arch/num_stones=951/stone-185.obj"},{"mesh":"arch/num_stones=951/stone-186.obj"},{"mesh":"arch/num_stones=951/stone-187.obj"},{"mesh":"arch/num_stones=951/stone-188.obj"},{"mesh":"arch/num_stones=951/stone-189.obj"},{"mesh":"arch/num_stones=951/stone-190.obj"},{"mesh":"arch/num_stones=951/stone-191.obj"},{"mesh":"arch/num_stones=951/stone-192.obj"},{"mesh":"arch/num_stones=951/stone-193.obj"},{"mesh":"arch/num_stones=951/stone-194.obj"},{"mesh":"arch/num_stones=951/stone-195.obj"},{"mesh":"arch/num_stones=951/stone-196.obj"},{"mesh":"arch/num_stones=951/stone-197.obj"},{"mesh":"arch/num_stones=951/stone-198.obj"},{"mesh":"arch/num_stones=951/stone-199.obj"},{"mesh":"arch/num_stones=951/stone-200.obj"},{"mesh":"arch/num_stones=951/stone-201.obj"},{"mesh":"arch/num_stones=951/stone-202.obj"},{"mesh":"arch/num_stones=951/stone-203.obj"},{"mesh":"arch/num_stones=951/stone-204.obj"},{"mesh":"arch/num_stones=951/stone-205.obj"},{"mesh":"arch/num_stones=951/stone-206.obj"},{"mesh":"arch/num_stones=951/stone-207.obj"},{"mesh":"arch/num_stones=951/stone-208.obj"},{"mesh":"arch/num_stones=951/stone-209.obj"},{"mesh":"arch/num_stones=951/stone-210.obj"},{"mesh":"arch/num_stones=951/stone-211.obj"},{"mesh":"arch/num_stones=951/stone-212.obj"},{"mesh":"arch/num_stones=951/stone-213.obj"},{"mesh":"arch/num_stones=951/stone-214.obj"},{"mesh":"arch/num_stones=951/stone-215.obj"},{"mesh":"arch/num_stones=951/stone-216.obj"},{"mesh":"arch/num_stones=951/stone-217.obj"},{"mesh":"arch/num_stones=951/stone-218.obj"},{"mesh":"arch/num_stones=951/stone-219.obj"},{"mesh":"arch/num_stones=951/stone-220.obj"},{"mesh":"arch/num_stones=951/stone-221.obj"},{"mesh":"arch/num_stones=951/stone-222.obj"},{"mesh":"arch/num_stones=951/stone-223.obj"},{"mesh":"arch/num_stones=951/stone-224.obj"},{"mesh":"arch/num_stones=951/stone-225.obj"},{"mesh":"arch/num_stones=951/stone-226.obj"},{"mesh":"arch/num_stones=951/stone-227.obj"},{"mesh":"arch/num_stones=951/stone-228.obj"},{"mesh":"arch/num_stones=951/stone-229.obj"},{"mesh":"arch/num_stones=951/stone-230.obj"},{"mesh":"arch/num_stones=951/stone-231.obj"},{"mesh":"arch/num_stones=951/stone-232.obj"},{"mesh":"arch/num_stones=951/stone-233.obj"},{"mesh":"arch/num_stones=951/stone-234.obj"},{"mesh":"arch/num_stones=951/stone-235.obj"},{"mesh":"arch/num_stones=951/stone-236.obj"},{"mesh":"arch/num_stones=951/stone-237.obj"},{"mesh":"arch/num_stones=951/stone-238.obj"},{"mesh":"arch/num_stones=951/stone-239.obj"},{"mesh":"arch/num_stones=951/stone-240.obj"},{"mesh":"arch/num_stones=951/stone-241.obj"},{"mesh":"arch/num_stones=951/stone-242.obj"},{"mesh":"arch/num_stones=951/stone-243.obj"},{"mesh":"arch/num_stones=951/stone-244.obj"},{"mesh":"arch/num_stones=951/stone-245.obj"},{"mesh":"arch/num_stones=951/stone-246.obj"},{"mesh":"arch/num_stones=951/stone-247.obj"},{"mesh":"arch/num_stones=951/stone-248.obj"},{"mesh":"arch/num_stones=951/stone-249.obj"},{"mesh":"arch/num_stones=951/stone-250.obj"},{"mesh":"arch/num_stones=951/stone-251.obj"},{"mesh":"arch/num_stones=951/stone-252.obj"},{"mesh":"arch/num_stones=951/stone-253.obj"},{"mesh":"arch/num_stones=951/stone-254.obj"},{"mesh":"arch/num_stones=951/stone-255.obj"},{"mesh":"arch/num_stones=951/stone-256.obj"},{"mesh":"arch/num_stones=951/stone-257.obj"},{"mesh":"arch/num_stones=951/stone-258.obj"},{"mesh":"arch/num_stones=951/stone-259.obj"},{"mesh":"arch/num_stones=951/stone-260.obj"},{"mesh":"arch/num_stones=951/stone-261.obj"},{"mesh":"arch/num_stones=951/stone-262.obj"},{"mesh":"arch/num_stones=951/stone-263.obj"},{"mesh":"arch/num_stones=951/stone-264.obj"},{"mesh":"arch/num_stones=951/stone-265.obj"},{"mesh":"arch/num_stones=951/stone-266.obj"},{"mesh":"arch/num_stones=951/stone-267.obj"},{"mesh":"arch/num_stones=951/stone-268.obj"},{"mesh":"arch/num_stones=951/stone-269.obj"},{"mesh":"arch/num_stones=951/stone-270.obj"},{"mesh":"arch/num_stones=951/stone-271.obj"},{"mesh":"arch/num_stones=951/stone-272.obj"},{"mesh":"arch/num_stones=951/stone-273.obj"},{"mesh":"arch/num_stones=951/stone-274.obj"},{"mesh":"arch/num_stones=951/stone-275.obj"},{"mesh":"arch/num_stones=951/stone-276.obj"},{"mesh":"arch/num_stones=951/stone-277.obj"},{"mesh":"arch/num_stones=951/stone-278.obj"},{"mesh":"arch/num_stones=951/stone-279.obj"},{"mesh":"arch/num_stones=951/stone-280.obj"},{"mesh":"arch/num_stones=951/stone-281.obj"},{"mesh":"arch/num_stones=951/stone-282.obj"},{"mesh":"arch/num_stones=951/stone-283.obj"},{"mesh":"arch/num_stones=951/stone-284.obj"},{"mesh":"arch/num_stones=951/stone-285.obj"},{"mesh":"arch/num_stones=951/stone-286.obj"},{"mesh":"arch/num_stones=951/stone-287.obj"},{"mesh":"arch/num_stones=951/stone-288.obj"},{"mesh":"arch/num_stones=951/stone-289.obj"},{"mesh":"arch/num_stones=951/stone-290.obj"},{"mesh":"arch/num_stones=951/stone-291.obj"},{"mesh":"arch/num_stones=951/stone-292.obj"},{"mesh":"arch/num_stones=951/stone-293.obj"},{"mesh":"arch/num_stones=951/stone-294.obj"},{"mesh":"arch/num_stones=951/stone-295.obj"},{"mesh":"arch/num_stones=951/stone-296.obj"},{"mesh":"arch/num_stones=951/stone-297.obj"},{"mesh":"arch/num_stones=951/stone-298.obj"},{"mesh":"arch/num_stones=951/stone-299.obj"},{"mesh":"arch/num_stones=951/stone-300.obj"},{"mesh":"arch/num_stones=951/stone-301.obj"},{"mesh":"arch/num_stones=951/stone-302.obj"},{"mesh":"arch/num_stones=951/stone-303.obj"},{"mesh":"arch/num_stones=951/stone-304.obj"},{"mesh":"arch/num_stones=951/stone-305.obj"},{"mesh":"arch/num_stones=951/stone-306.obj"},{"mesh":"arch/num_stones=951/stone-307.obj"},{"mesh":"arch/num_stones=951/stone-308.obj"},{"mesh":"arch/num_stones=951/stone-309.obj"},{"mesh":"arch/num_stones=951/stone-310.obj"},{"mesh":"arch/num_stones=951/stone-311.obj"},{"mesh":"arch/num_stones=951/stone-312.obj"},{"mesh":"arch/num_stones=951/stone-313.obj"},{"mesh":"arch/num_stones=951/stone-314.obj"},{"mesh":"arch/num_stones=951/stone-315.obj"},{"mesh":"arch/num_stones=951/stone-316.obj"},{"mesh":"arch/num_stones=951/stone-317.obj"},{"mesh":"arch/num_stones=951/stone-318.obj"},{"mesh":"arch/num_stones=951/stone-319.obj"},{"mesh":"arch/num_stones=951/stone-320.obj"},{"mesh":"arch/num_stones=951/stone-321.obj"},{"mesh":"arch/num_stones=951/stone-322.obj"},{"mesh":"arch/num_stones=951/stone-323.obj"},{"mesh":"arch/num_stones=951/stone-324.obj"},{"mesh":"arch/num_stones=951/stone-325.obj"},{"mesh":"arch/num_stones=951/stone-326.obj"},{"mesh":"arch/num_stones=951/stone-327.obj"},{"mesh":"arch/num_stones=951/stone-328.obj"},{"mesh":"arch/num_stones=951/stone-329.obj"},{"mesh":"arch/num_stones=951/stone-330.obj"},{"mesh":"arch/num_stones=951/stone-331.obj"},{"mesh":"arch/num_stones=951/stone-332.obj"},{"mesh":"arch/num_stones=951/stone-333.obj"},{"mesh":"arch/num_stones=951/stone-334.obj"},{"mesh":"arch/num_stones=951/stone-335.obj"},{"mesh":"arch/num_stones=951/stone-336.obj"},{"mesh":"arch/num_stones=951/stone-337.obj"},{"mesh":"arch/num_stones=951/stone-338.obj"},{"mesh":"arch/num_stones=951/stone-339.obj"},{"mesh":"arch/num_stones=951/stone-340.obj"},{"mesh":"arch/num_stones=951/stone-341.obj"},{"mesh":"arch/num_stones=951/stone-342.obj"},{"mesh":"arch/num_stones=951/stone-343.obj"},{"mesh":"arch/num_stones=951/stone-344.obj"},{"mesh":"arch/num_stones=951/stone-345.obj"},{"mesh":"arch/num_stones=951/stone-346.obj"},{"mesh":"arch/num_stones=951/stone-347.obj"},{"mesh":"arch/num_stones=951/stone-348.obj"},{"mesh":"arch/num_stones=951/stone-349.obj"},{"mesh":"arch/num_stones=951/stone-350.obj"},{"mesh":"arch/num_stones=951/stone-351.obj"},{"mesh":"arch/num_stones=951/stone-352.obj"},{"mesh":"arch/num_stones=951/stone-353.obj"},{"mesh":"arch/num_stones=951/stone-354.obj"},{"mesh":"arch/num_stones=951/stone-355.obj"},{"mesh":"arch/num_stones=951/stone-356.obj"},{"mesh":"arch/num_stones=951/stone-357.obj"},{"mesh":"arch/num_stones=951/stone-358.obj"},{"mesh":"arch/num_stones=951/stone-359.obj"},{"mesh":"arch/num_stones=951/stone-360.obj"},{"mesh":"arch/num_stones=951/stone-361.obj"},{"mesh":"arch/num_stones=951/stone-362.obj"},{"mesh":"arch/num_stones=951/stone-363.obj"},{"mesh":"arch/num_stones=951/stone-364.obj"},{"mesh":"arch/num_stones=951/stone-365.obj"},{"mesh":"arch/num_stones=951/stone-366.obj"},{"mesh":"arch/num_stones=951/stone-367.obj"},{"mesh":"arch/num_stones=951/stone-368.obj"},{"mesh":"arch/num_stones=951/stone-369.obj"},{"mesh":"arch/num_stones=951/stone-370.obj"},{"mesh":"arch/num_stones=951/stone-371.obj"},{"mesh":"arch/num_stones=951/stone-372.obj"},{"mesh":"arch/num_stones=951/stone-373.obj"},{"mesh":"arch/num_stones=951/stone-374.obj"},{"mesh":"arch/num_stones=951/stone-375.obj"},{"mesh":"arch/num_stones=951/stone-376.obj"},{"mesh":"arch/num_stones=951/stone-377.obj"},{"mesh":"arch/num_stones=951/stone-378.obj"},{"mesh":"arch/num_stones=951/stone-379.obj"},{"mesh":"arch/num_stones=951/stone-380.obj"},{"mesh":"arch/num_stones=951/stone-381.obj"},{"mesh":"arch/num_stones=951/stone-382.obj"},{"mesh":"arch/num_stones=951/stone-383.obj"},{"mesh":"arch/num_stones=951/stone-384.obj"},{"mesh":"arch/num_stones=951/stone-385.obj"},{"mesh":"arch/num_stones=951/stone-386.obj"},{"mesh":"arch/num_stones=951/stone-387.obj"},{"mesh":"arch/num_stones=951/stone-388.obj"},{"mesh":"arch/num_stones=951/stone-389.obj"},{"mesh":"arch/num_stones=951/stone-390.obj"},{"mesh":"arch/num_stones=951/stone-391.obj"},{"mesh":"arch/num_stones=951/stone-392.obj"},{"mesh":"arch/num_stones=951/stone-393.obj"},{"mesh":"arch/num_stones=951/stone-394.obj"},{"mesh":"arch/num_stones=951/stone-395.obj"},{"mesh":"arch/num_stones=951/stone-396.obj"},{"mesh":"arch/num_stones=951/stone-397.obj"},{"mesh":"arch/num_stones=951/stone-398.obj"},{"mesh":"arch/num_stones=951/stone-399.obj"},{"mesh":"arch/num_stones=951/stone-400.obj"},{"mesh":"arch/num_stones=951/stone-401.obj"},{"mesh":"arch/num_stones=951/stone-402.obj"},{"mesh":"arch/num_stones=951/stone-403.obj"},{"mesh":"arch/num_stones=951/stone-404.obj"},{"mesh":"arch/num_stones=951/stone-405.obj"},{"mesh":"arch/num_stones=951/stone-406.obj"},{"mesh":"arch/num_stones=951/stone-407.obj"},{"mesh":"arch/num_stones=951/stone-408.obj"},{"mesh":"arch/num_stones=951/stone-409.obj"},{"mesh":"arch/num_stones=951/stone-410.obj"},{"mesh":"arch/num_stones=951/stone-411.obj"},{"mesh":"arch/num_stones=951/stone-412.obj"},{"mesh":"arch/num_stones=951/stone-413.obj"},{"mesh":"arch/num_stones=951/stone-414.obj"},{"mesh":"arch/num_stones=951/stone-415.obj"},{"mesh":"arch/num_stones=951/stone-416.obj"},{"mesh":"arch/num_stones=951/stone-417.obj"},{"mesh":"arch/num_stones=951/stone-418.obj"},{"mesh":"arch/num_stones=951/stone-419.obj"},{"mesh":"arch/num_stones=951/stone-420.obj"},{"mesh":"arch/num_stones=951/stone-421.obj"},{"mesh":"arch/num_stones=951/stone-422.obj"},{"mesh":"arch/num_stones=951/stone-423.obj"},{"mesh":"arch/num_stones=951/stone-424.obj"},{"mesh":"arch/num_stones=951/stone-425.obj"},{"mesh":"arch/num_stones=951/stone-426.obj"},{"mesh":"arch/num_stones=951/stone-427.obj"},{"mesh":"arch/num_stones=951/stone-428.obj"},{"mesh":"arch/num_stones=951/stone-429.obj"},{"mesh":"arch/num_stones=951/stone-430.obj"},{"mesh":"arch/num_stones=951/stone-431.obj"},{"mesh":"arch/num_stones=951/stone-432.obj"},{"mesh":"arch/num_stones=951/stone-433.obj"},{"mesh":"arch/num_stones=951/stone-434.obj"},{"mesh":"arch/num_stones=951/stone-435.obj"},{"mesh":"arch/num_stones=951/stone-436.obj"},{"mesh":"arch/num_stones=951/stone-437.obj"},{"mesh":"arch/num_stones=951/stone-438.obj"},{"mesh":"arch/num_stones=951/stone-439.obj"},{"mesh":"arch/num_stones=951/stone-440.obj"},{"mesh":"arch/num_stones=951/stone-441.obj"},{"mesh":"arch/num_stones=951/stone-442.obj"},{"mesh":"arch/num_stones=951/stone-443.obj"},{"mesh":"arch/num_stones=951/stone-444.obj"},{"mesh":"arch/num_stones=951/stone-445.obj"},{"mesh":"arch/num_stones=951/stone-446.obj"},{"mesh":"arch/num_stones=951/stone-447.obj"},{"mesh":"arch/num_stones=951/stone-448.obj"},{"mesh":"arch/num_stones=951/stone-449.obj"},{"mesh":"arch/num_stones=951/stone-450.obj"},{"mesh":"arch/num_stones=951/stone-451.obj"},{"mesh":"arch/num_stones=951/stone-452.obj"},{"mesh":"arch/num_stones=951/stone-453.obj"},{"mesh":"arch/num_stones=951/stone-454.obj"},{"mesh":"arch/num_stones=951/stone-455.obj"},{"mesh":"arch/num_stones=951/stone-456.obj"},{"mesh":"arch/num_stones=951/stone-457.obj"},{"mesh":"arch/num_stones=951/stone-458.obj"},{"mesh":"arch/num_stones=951/stone-459.obj"},{"mesh":"arch/num_stones=951/stone-460.obj"},{"mesh":"arch/num_stones=951/stone-461.obj"},{"mesh":"arch/num_stones=951/stone-462.obj"},{"mesh":"arch/num_stones=951/stone-463.obj"},{"mesh":"arch/num_stones=951/stone-464.obj"},{"mesh":"arch/num_stones=951/stone-465.obj"},{"mesh":"arch/num_stones=951/stone-466.obj"},{"mesh":"arch/num_stones=951/stone-467.obj"},{"mesh":"arch/num_stones=951/stone-468.obj"},{"mesh":"arch/num_stones=951/stone-469.obj"},{"mesh":"arch/num_stones=951/stone-470.obj"},{"mesh":"arch/num_stones=951/stone-471.obj"},{"mesh":"arch/num_stones=951/stone-472.obj"},{"mesh":"arch/num_stones=951/stone-473.obj"},{"mesh":"arch/num_stones=951/stone-474.obj"},{"mesh":"arch/num_stones=951/stone-475.obj"},{"mesh":"arch/num_stones=951/stone-476.obj"},{"mesh":"arch/num_stones=951/stone-477.obj"},{"mesh":"arch/num_stones=951/stone-478.obj"},{"mesh":"arch/num_stones=951/stone-479.obj"},{"mesh":"arch/num_stones=951/stone-480.obj"},{"mesh":"arch/num_stones=951/stone-481.obj"},{"mesh":"arch/num_stones=951/stone-482.obj"},{"mesh":"arch/num_stones=951/stone-483.obj"},{"mesh":"arch/num_stones=951/stone-484.obj"},{"mesh":"arch/num_stones=951/stone-485.obj"},{"mesh":"arch/num_stones=951/stone-486.obj"},{"mesh":"arch/num_stones=951/stone-487.obj"},{"mesh":"arch/num_stones=951/stone-488.obj"},{"mesh":"arch/num_stones=951/stone-489.obj"},{"mesh":"arch/num_stones=951/stone-490.obj"},{"mesh":"arch/num_stones=951/stone-491.obj"},{"mesh":"arch/num_stones=951/stone-492.obj"},{"mesh":"arch/num_stones=951/stone-493.obj"},{"mesh":"arch/num_stones=951/stone-494.obj"},{"mesh":"arch/num_stones=951/stone-495.obj"},{"mesh":"arch/num_stones=951/stone-496.obj"},{"mesh":"arch/num_stones=951/stone-497.obj"},{"mesh":"arch/num_stones=951/stone-498.obj"},{"mesh":"arch/num_stones=951/stone-499.obj"},{"mesh":"arch/num_stones=951/stone-500.obj"},{"mesh":"arch/num_stones=951/stone-501.obj"},{"mesh":"arch/num_stones=951/stone-502.obj"},{"mesh":"arch/num_stones=951/stone-503.obj"},{"mesh":"arch/num_stones=951/stone-504.obj"},{"mesh":"arch/num_stones=951/stone-505.obj"},{"mesh":"arch/num_stones=951/stone-506.obj"},{"mesh":"arch/num_stones=951/stone-507.obj"},{"mesh":"arch/num_stones=951/stone-508.obj"},{"mesh":"arch/num_stones=951/stone-509.obj"},{"mesh":"arch/num_stones=951/stone-510.obj"},{"mesh":"arch/num_stones=951/stone-511.obj"},{"mesh":"arch/num_stones=951/stone-512.obj"},{"mesh":"arch/num_stones=951/stone-513.obj"},{"mesh":"arch/num_stones=951/stone-514.obj"},{"mesh":"arch/num_stones=951/stone-515.obj"},{"mesh":"arch/num_stones=951/stone-516.obj"},{"mesh":"arch/num_stones=951/stone-517.obj"},{"mesh":"arch/num_stones=951/stone-518.obj"},{"mesh":"arch/num_stones=951/stone-519.obj"},{"mesh":"arch/num_stones=951/stone-520.obj"},{"mesh":"arch/num_stones=951/stone-521.obj"},{"mesh":"arch/num_stones=951/stone-522.obj"},{"mesh":"arch/num_stones=951/stone-523.obj"},{"mesh":"arch/num_stones=951/stone-524.obj"},{"mesh":"arch/num_stones=951/stone-525.obj"},{"mesh":"arch/num_stones=951/stone-526.obj"},{"mesh":"arch/num_stones=951/stone-527.obj"},{"mesh":"arch/num_stones=951/stone-528.obj"},{"mesh":"arch/num_stones=951/stone-529.obj"},{"mesh":"arch/num_stones=951/stone-530.obj"},{"mesh":"arch/num_stones=951/stone-531.obj"},{"mesh":"arch/num_stones=951/stone-532.obj"},{"mesh":"arch/num_stones=951/stone-533.obj"},{"mesh":"arch/num_stones=951/stone-534.obj"},{"mesh":"arch/num_stones=951/stone-535.obj"},{"mesh":"arch/num_stones=951/stone-536.obj"},{"mesh":"arch/num_stones=951/stone-537.obj"},{"mesh":"arch/num_stones=951/stone-538.obj"},{"mesh":"arch/num_stones=951/stone-539.obj"},{"mesh":"arch/num_stones=951/stone-540.obj"},{"mesh":"arch/num_stones=951/stone-541.obj"},{"mesh":"arch/num_stones=951/stone-542.obj"},{"mesh":"arch/num_stones=951/stone-543.obj"},{"mesh":"arch/num_stones=951/stone-544.obj"},{"mesh":"arch/num_stones=951/stone-545.obj"},{"mesh":"arch/num_stones=951/stone-546.obj"},{"mesh":"arch/num_stones=951/stone-547.obj"},{"mesh":"arch/num_stones=951/stone-548.obj"},{"mesh":"arch/num_stones=951/stone-549.obj"},{"mesh":"arch/num_stones=951/stone-550.obj"},{"mesh":"arch/num_stones=951/stone-551.obj"},{"mesh":"arch/num_stones=951/stone-552.obj"},{"mesh":"arch/num_stones=951/stone-553.obj"},{"mesh":"arch/num_stones=951/stone-554.obj"},{"mesh":"arch/num_stones=951/stone-555.obj"},{"mesh":"arch/num_stones=951/stone-556.obj"},{"mesh":"arch/num_stones=951/stone-557.obj"},{"mesh":"arch/num_stones=951/stone-558.obj"},{"mesh":"arch/num_stones=951/stone-559.obj"},{"mesh":"arch/num_stones=951/stone-560.obj"},{"mesh":"arch/num_stones=951/stone-561.obj"},{"mesh":"arch/num_stones=951/stone-562.obj"},{"mesh":"arch/num_stones=951/stone-563.obj"},{"mesh":"arch/num_stones=951/stone-564.obj"},{"mesh":"arch/num_stones=951/stone-565.obj"},{"mesh":"arch/num_stones=951/stone-566.obj"},{"mesh":"arch/num_stones=951/stone-567.obj"},{"mesh":"arch/num_stones=951/stone-568.obj"},{"mesh":"arch/num_stones=951/stone-569.obj"},{"mesh":"arch/num_stones=951/stone-570.obj"},{"mesh":"arch/num_stones=951/stone-571.obj"},{"mesh":"arch/num_stones=951/stone-572.obj"},{"mesh":"arch/num_stones=951/stone-573.obj"},{"mesh":"arch/num_stones=951/stone-574.obj"},{"mesh":"arch/num_stones=951/stone-575.obj"},{"mesh":"arch/num_stones=951/stone-576.obj"},{"mesh":"arch/num_stones=951/stone-577.obj"},{"mesh":"arch/num_stones=951/stone-578.obj"},{"mesh":"arch/num_stones=951/stone-579.obj"},{"mesh":"arch/num_stones=951/stone-580.obj"},{"mesh":"arch/num_stones=951/stone-581.obj"},{"mesh":"arch/num_stones=951/stone-582.obj"},{"mesh":"arch/num_stones=951/stone-583.obj"},{"mesh":"arch/num_stones=951/stone-584.obj"},{"mesh":"arch/num_stones=951/stone-585.obj"},{"mesh":"arch/num_stones=951/stone-586.obj"},{"mesh":"arch/num_stones=951/stone-587.obj"},{"mesh":"arch/num_stones=951/stone-588.obj"},{"mesh":"arch/num_stones=951/stone-589.obj"},{"mesh":"arch/num_stones=951/stone-590.obj"},{"mesh":"arch/num_stones=951/stone-591.obj"},{"mesh":"arch/num_stones=951/stone-592.obj"},{"mesh":"arch/num_stones=951/stone-593.obj"},{"mesh":"arch/num_stones=951/stone-594.obj"},{"mesh":"arch/num_stones=951/stone-595.obj"},{"mesh":"arch/num_stones=951/stone-596.obj"},{"mesh":"arch/num_stones=951/stone-597.obj"},{"mesh":"arch/num_stones=951/stone-598.obj"},{"mesh":"arch/num_stones=951/stone-599.obj"},{"mesh":"arch/num_stones=951/stone-600.obj"},{"mesh":"arch/num_stones=951/stone-601.obj"},{"mesh":"arch/num_stones=951/stone-602.obj"},{"mesh":"arch/num_stones=951/stone-603.obj"},{"mesh":"arch/num_stones=951/stone-604.obj"},{"mesh":"arch/num_stones=951/stone-605.obj"},{"mesh":"arch/num_stones=951/stone-606.obj"},{"mesh":"arch/num_stones=951/stone-607.obj"},{"mesh":"arch/num_stones=951/stone-608.obj"},{"mesh":"arch/num_stones=951/stone-609.obj"},{"mesh":"arch/num_stones=951/stone-610.obj"},{"mesh":"arch/num_stones=951/stone-611.obj"},{"mesh":"arch/num_stones=951/stone-612.obj"},{"mesh":"arch/num_stones=951/stone-613.obj"},{"mesh":"arch/num_stones=951/stone-614.obj"},{"mesh":"arch/num_stones=951/stone-615.obj"},{"mesh":"arch/num_stones=951/stone-616.obj"},{"mesh":"arch/num_stones=951/stone-617.obj"},{"mesh":"arch/num_stones=951/stone-618.obj"},{"mesh":"arch/num_stones=951/stone-619.obj"},{"mesh":"arch/num_stones=951/stone-620.obj"},{"mesh":"arch/num_stones=951/stone-621.obj"},{"mesh":"arch/num_stones=951/stone-622.obj"},{"mesh":"arch/num_stones=951/stone-623.obj"},{"mesh":"arch/num_stones=951/stone-624.obj"},{"mesh":"arch/num_stones=951/stone-625.obj"},{"mesh":"arch/num_stones=951/stone-626.obj"},{"mesh":"arch/num_stones=951/stone-627.obj"},{"mesh":"arch/num_stones=951/stone-628.obj"},{"mesh":"arch/num_stones=951/stone-629.obj"},{"mesh":"arch/num_stones=951/stone-630.obj"},{"mesh":"arch/num_stones=951/stone-631.obj"},{"mesh":"arch/num_stones=951/stone-632.obj"},{"mesh":"arch/num_stones=951/stone-633.obj"},{"mesh":"arch/num_stones=951/stone-634.obj"},{"mesh":"arch/num_stones=951/stone-635.obj"},{"mesh":"arch/num_stones=951/stone-636.obj"},{"mesh":"arch/num_stones=951/stone-637.obj"},{"mesh":"arch/num_stones=951/stone-638.obj"},{"mesh":"arch/num_stones=951/stone-639.obj"},{"mesh":"arch/num_stones=951/stone-640.obj"},{"mesh":"arch/num_stones=951/stone-641.obj"},{"mesh":"arch/num_stones=951/stone-642.obj"},{"mesh":"arch/num_stones=951/stone-643.obj"},{"mesh":"arch/num_stones=951/stone-644.obj"},{"mesh":"arch/num_stones=951/stone-645.obj"},{"mesh":"arch/num_stones=951/stone-646.obj"},{"mesh":"arch/num_stones=951/stone-647.obj"},{"mesh":"arch/num_stones=951/stone-648.obj"},{"mesh":"arch/num_stones=951/stone-649.obj"},{"mesh":"arch/num_stones=951/stone-650.obj"},{"mesh":"arch/num_stones=951/stone-651.obj"},{"mesh":"arch/num_stones=951/stone-652.obj"},{"mesh":"arch/num_stones=951/stone-653.obj"},{"mesh":"arch/num_stones=951/stone-654.obj"},{"mesh":"arch/num_stones=951/stone-655.obj"},{"mesh":"arch/num_stones=951/stone-656.obj"},{"mesh":"arch/num_stones=951/stone-657.obj"},{"mesh":"arch/num_stones=951/stone-658.obj"},{"mesh":"arch/num_stones=951/stone-659.obj"},{"mesh":"arch/num_stones=951/stone-660.obj"},{"mesh":"arch/num_stones=951/stone-661.obj"},{"mesh":"arch/num_stones=951/stone-662.obj"},{"mesh":"arch/num_stones=951/stone-663.obj"},{"mesh":"arch/num_stones=951/stone-664.obj"},{"mesh":"arch/num_stones=951/stone-665.obj"},{"mesh":"arch/num_stones=951/stone-666.obj"},{"mesh":"arch/num_stones=951/stone-667.obj"},{"mesh":"arch/num_stones=951/stone-668.obj"},{"mesh":"arch/num_stones=951/stone-669.obj"},{"mesh":"arch/num_stones=951/stone-670.obj"},{"mesh":"arch/num_stones=951/stone-671.obj"},{"mesh":"arch/num_stones=951/stone-672.obj"},{"mesh":"arch/num_stones=951/stone-673.obj"},{"mesh":"arch/num_stones=951/stone-674.obj"},{"mesh":"arch/num_stones=951/stone-675.obj"},{"mesh":"arch/num_stones=951/stone-676.obj"},{"mesh":"arch/num_stones=951/stone-677.obj"},{"mesh":"arch/num_stones=951/stone-678.obj"},{"mesh":"arch/num_stones=951/stone-679.obj"},{"mesh":"arch/num_stones=951/stone-680.obj"},{"mesh":"arch/num_stones=951/stone-681.obj"},{"mesh":"arch/num_stones=951/stone-682.obj"},{"mesh":"arch/num_stones=951/stone-683.obj"},{"mesh":"arch/num_stones=951/stone-684.obj"},{"mesh":"arch/num_stones=951/stone-685.obj"},{"mesh":"arch/num_stones=951/stone-686.obj"},{"mesh":"arch/num_stones=951/stone-687.obj"},{"mesh":"arch/num_stones=951/stone-688.obj"},{"mesh":"arch/num_stones=951/stone-689.obj"},{"mesh":"arch/num_stones=951/stone-690.obj"},{"mesh":"arch/num_stones=951/stone-691.obj"},{"mesh":"arch/num_stones=951/stone-692.obj"},{"mesh":"arch/num_stones=951/stone-693.obj"},{"mesh":"arch/num_stones=951/stone-694.obj"},{"mesh":"arch/num_stones=951/stone-695.obj"},{"mesh":"arch/num_stones=951/stone-696.obj"},{"mesh":"arch/num_stones=951/stone-697.obj"},{"mesh":"arch/num_stones=951/stone-698.obj"},{"mesh":"arch/num_stones=951/stone-699.obj"},{"mesh":"arch/num_stones=951/stone-700.obj"},{"mesh":"arch/num_stones=951/stone-701.obj"},{"mesh":"arch/num_stones=951/stone-702.obj"},{"mesh":"arch/num_stones=951/stone-703.obj"},{"mesh":"arch/num_stones=951/stone-704.obj"},{"mesh":"arch/num_stones=951/stone-705.obj"},{"mesh":"arch/num_stones=951/stone-706.obj"},{"mesh":"arch/num_stones=951/stone-707.obj"},{"mesh":"arch/num_stones=951/stone-708.obj"},{"mesh":"arch/num_stones=951/stone-709.obj"},{"mesh":"arch/num_stones=951/stone-710.obj"},{"mesh":"arch/num_stones=951/stone-711.obj"},{"mesh":"arch/num_stones=951/stone-712.obj"},{"mesh":"arch/num_stones=951/stone-713.obj"},{"mesh":"arch/num_stones=951/stone-714.obj"},{"mesh":"arch/num_stones=951/stone-715.obj"},{"mesh":"arch/num_stones=951/stone-716.obj"},{"mesh":"arch/num_stones=951/stone-717.obj"},{"mesh":"arch/num_stones=951/stone-718.obj"},{"mesh":"arch/num_stones=951/stone-719.obj"},{"mesh":"arch/num_stones=951/stone-720.obj"},{"mesh":"arch/num_stones=951/stone-721.obj"},{"mesh":"arch/num_stones=951/stone-722.obj"},{"mesh":"arch/num_stones=951/stone-723.obj"},{"mesh":"arch/num_stones=951/stone-724.obj"},{"mesh":"arch/num_stones=951/stone-725.obj"},{"mesh":"arch/num_stones=951/stone-726.obj"},{"mesh":"arch/num_stones=951/stone-727.obj"},{"mesh":"arch/num_stones=951/stone-728.obj"},{"mesh":"arch/num_stones=951/stone-729.obj"},{"mesh":"arch/num_stones=951/stone-730.obj"},{"mesh":"arch/num_stones=951/stone-731.obj"},{"mesh":"arch/num_stones=951/stone-732.obj"},{"mesh":"arch/num_stones=951/stone-733.obj"},{"mesh":"arch/num_stones=951/stone-734.obj"},{"mesh":"arch/num_stones=951/stone-735.obj"},{"mesh":"arch/num_stones=951/stone-736.obj"},{"mesh":"arch/num_stones=951/stone-737.obj"},{"mesh":"arch/num_stones=951/stone-738.obj"},{"mesh":"arch/num_stones=951/stone-739.obj"},{"mesh":"arch/num_stones=951/stone-740.obj"},{"mesh":"arch/num_stones=951/stone-741.obj"},{"mesh":"arch/num_stones=951/stone-742.obj"},{"mesh":"arch/num_stones=951/stone-743.obj"},{"mesh":"arch/num_stones=951/stone-744.obj"},{"mesh":"arch/num_stones=951/stone-745.obj"},{"mesh":"arch/num_stones=951/stone-746.obj"},{"mesh":"arch/num_stones=951/stone-747.obj"},{"mesh":"arch/num_stones=951/stone-748.obj"},{"mesh":"arch/num_stones=951/stone-749.obj"},{"mesh":"arch/num_stones=951/stone-750.obj"},{"mesh":"arch/num_stones=951/stone-751.obj"},{"mesh":"arch/num_stones=951/stone-752.obj"},{"mesh":"arch/num_stones=951/stone-753.obj"},{"mesh":"arch/num_stones=951/stone-754.obj"},{"mesh":"arch/num_stones=951/stone-755.obj"},{"mesh":"arch/num_stones=951/stone-756.obj"},{"mesh":"arch/num_stones=951/stone-757.obj"},{"mesh":"arch/num_stones=951/stone-758.obj"},{"mesh":"arch/num_stones=951/stone-759.obj"},{"mesh":"arch/num_stones=951/stone-760.obj"},{"mesh":"arch/num_stones=951/stone-761.obj"},{"mesh":"arch/num_stones=951/stone-762.obj"},{"mesh":"arch/num_stones=951/stone-763.obj"},{"mesh":"arch/num_stones=951/stone-764.obj"},{"mesh":"arch/num_stones=951/stone-765.obj"},{"mesh":"arch/num_stones=951/stone-766.obj"},{"mesh":"arch/num_stones=951/stone-767.obj"},{"mesh":"arch/num_stones=951/stone-768.obj"},{"mesh":"arch/num_stones=951/stone-769.obj"},{"mesh":"arch/num_stones=951/stone-770.obj"},{"mesh":"arch/num_stones=951/stone-771.obj"},{"mesh":"arch/num_stones=951/stone-772.obj"},{"mesh":"arch/num_stones=951/stone-773.obj"},{"mesh":"arch/num_stones=951/stone-774.obj"},{"mesh":"arch/num_stones=951/stone-775.obj"},{"mesh":"arch/num_stones=951/stone-776.obj"},{"mesh":"arch/num_stones=951/stone-777.obj"},{"mesh":"arch/num_stones=951/stone-778.obj"},{"mesh":"arch/num_stones=951/stone-779.obj"},{"mesh":"arch/num_stones=951/stone-780.obj"},{"mesh":"arch/num_stones=951/stone-781.obj"},{"mesh":"arch/num_stones=951/stone-782.obj"},{"mesh":"arch/num_stones=951/stone-783.obj"},{"mesh":"arch/num_stones=951/stone-784.obj"},{"mesh":"arch/num_stones=951/stone-785.obj"},{"mesh":"arch/num_stones=951/stone-786.obj"},{"mesh":"arch/num_stones=951/stone-787.obj"},{"mesh":"arch/num_stones=951/stone-788.obj"},{"mesh":"arch/num_stones=951/stone-789.obj"},{"mesh":"arch/num_stones=951/stone-790.obj"},{"mesh":"arch/num_stones=951/stone-791.obj"},{"mesh":"arch/num_stones=951/stone-792.obj"},{"mesh":"arch/num_stones=951/stone-793.obj"},{"mesh":"arch/num_stones=951/stone-794.obj"},{"mesh":"arch/num_stones=951/stone-795.obj"},{"mesh":"arch/num_stones=951/stone-796.obj"},{"mesh":"arch/num_stones=951/stone-797.obj"},{"mesh":"arch/num_stones=951/stone-798.obj"},{"mesh":"arch/num_stones=951/stone-799.obj"},{"mesh":"arch/num_stones=951/stone-800.obj"},{"mesh":"arch/num_stones=951/stone-801.obj"},{"mesh":"arch/num_stones=951/stone-802.obj"},{"mesh":"arch/num_stones=951/stone-803.obj"},{"mesh":"arch/num_stones=951/stone-804.obj"},{"mesh":"arch/num_stones=951/stone-805.obj"},{"mesh":"arch/num_stones=951/stone-806.obj"},{"mesh":"arch/num_stones=951/stone-807.obj"},{"mesh":"arch/num_stones=951/stone-808.obj"},{"mesh":"arch/num_stones=951/stone-809.obj"},{"mesh":"arch/num_stones=951/stone-810.obj"},{"mesh":"arch/num_stones=951/stone-811.obj"},{"mesh":"arch/num_stones=951/stone-812.obj"},{"mesh":"arch/num_stones=951/stone-813.obj"},{"mesh":"arch/num_stones=951/stone-814.obj"},{"mesh":"arch/num_stones=951/stone-815.obj"},{"mesh":"arch/num_stones=951/stone-816.obj"},{"mesh":"arch/num_stones=951/stone-817.obj"},{"mesh":"arch/num_stones=951/stone-818.obj"},{"mesh":"arch/num_stones=951/stone-819.obj"},{"mesh":"arch/num_stones=951/stone-820.obj"},{"mesh":"arch/num_stones=951/stone-821.obj"},{"mesh":"arch/num_stones=951/stone-822.obj"},{"mesh":"arch/num_stones=951/stone-823.obj"},{"mesh":"arch/num_stones=951/stone-824.obj"},{"mesh":"arch/num_stones=951/stone-825.obj"},{"mesh":"arch/num_stones=951/stone-826.obj"},{"mesh":"arch/num_stones=951/stone-827.obj"},{"mesh":"arch/num_stones=951/stone-828.obj"},{"mesh":"arch/num_stones=951/stone-829.obj"},{"mesh":"arch/num_stones=951/stone-830.obj"},{"mesh":"arch/num_stones=951/stone-831.obj"},{"mesh":"arch/num_stones=951/stone-832.obj"},{"mesh":"arch/num_stones=951/stone-833.obj"},{"mesh":"arch/num_stones=951/stone-834.obj"},{"mesh":"arch/num_stones=951/stone-835.obj"},{"mesh":"arch/num_stones=951/stone-836.obj"},{"mesh":"arch/num_stones=951/stone-837.obj"},{"mesh":"arch/num_stones=951/stone-838.obj"},{"mesh":"arch/num_stones=951/stone-839.obj"},{"mesh":"arch/num_stones=951/stone-840.obj"},{"mesh":"arch/num_stones=951/stone-841.obj"},{"mesh":"arch/num_stones=951/stone-842.obj"},{"mesh":"arch/num_stones=951/stone-843.obj"},{"mesh":"arch/num_stones=951/stone-844.obj"},{"mesh":"arch/num_stones=951/stone-845.obj"},{"mesh":"arch/num_stones=951/stone-846.obj"},{"mesh":"arch/num_stones=951/stone-847.obj"},{"mesh":"arch/num_stones=951/stone-848.obj"},{"mesh":"arch/num_stones=951/stone-849.obj"},{"mesh":"arch/num_stones=951/stone-850.obj"},{"mesh":"arch/num_stones=951/stone-851.obj"},{"mesh":"arch/num_stones=951/stone-852.obj"},{"mesh":"arch/num_stones=951/stone-853.obj"},{"mesh":"arch/num_stones=951/stone-854.obj"},{"mesh":"arch/num_stones=951/stone-855.obj"},{"mesh":"arch/num_stones=951/stone-856.obj"},{"mesh":"arch/num_stones=951/stone-857.obj"},{"mesh":"arch/num_stones=951/stone-858.obj"},{"mesh":"arch/num_stones=951/stone-859.obj"},{"mesh":"arch/num_stones=951/stone-860.obj"},{"mesh":"arch/num_stones=951/stone-861.obj"},{"mesh":"arch/num_stones=951/stone-862.obj"},{"mesh":"arch/num_stones=951/stone-863.obj"},{"mesh":"arch/num_stones=951/stone-864.obj"},{"mesh":"arch/num_stones=951/stone-865.obj"},{"mesh":"arch/num_stones=951/stone-866.obj"},{"mesh":"arch/num_stones=951/stone-867.obj"},{"mesh":"arch/num_stones=951/stone-868.obj"},{"mesh":"arch/num_stones=951/stone-869.obj"},{"mesh":"arch/num_stones=951/stone-870.obj"},{"mesh":"arch/num_stones=951/stone-871.obj"},{"mesh":"arch/num_stones=951/stone-872.obj"},{"mesh":"arch/num_stones=951/stone-873.obj"},{"mesh":"arch/num_stones=951/stone-874.obj"},{"mesh":"arch/num_stones=951/stone-875.obj"},{"mesh":"arch/num_stones=951/stone-876.obj"},{"mesh":"arch/num_stones=951/stone-877.obj"},{"mesh":"arch/num_stones=951/stone-878.obj"},{"mesh":"arch/num_stones=951/stone-879.obj"},{"mesh":"arch/num_stones=951/stone-880.obj"},{"mesh":"arch/num_stones=951/stone-881.obj"},{"mesh":"arch/num_stones=951/stone-882.obj"},{"mesh":"arch/num_stones=951/stone-883.obj"},{"mesh":"arch/num_stones=951/stone-884.obj"},{"mesh":"arch/num_stones=951/stone-885.obj"},{"mesh":"arch/num_stones=951/stone-886.obj"},{"mesh":"arch/num_stones=951/stone-887.obj"},{"mesh":"arch/num_stones=951/stone-888.obj"},{"mesh":"arch/num_stones=951/stone-889.obj"},{"mesh":"arch/num_stones=951/stone-890.obj"},{"mesh":"arch/num_stones=951/stone-891.obj"},{"mesh":"arch/num_stones=951/stone-892.obj"},{"mesh":"arch/num_stones=951/stone-893.obj"},{"mesh":"arch/num_stones=951/stone-894.obj"},{"mesh":"arch/num_stones=951/stone-895.obj"},{"mesh":"arch/num_stones=951/stone-896.obj"},{"mesh":"arch/num_stones=951/stone-897.obj"},{"mesh":"arch/num_stones=951/stone-898.obj"},{"mesh":"arch/num_stones=951/stone-899.obj"},{"mesh":"arch/num_stones=951/stone-900.obj"},{"mesh":"arch/num_stones=951/stone-901.obj"},{"mesh":"arch/num_stones=951/stone-902.obj"},{"mesh":"arch/num_stones=951/stone-903.obj"},{"mesh":"arch/num_stones=951/stone-904.obj"},{"mesh":"arch/num_stones=951/stone-905.obj"},{"mesh":"arch/num_stones=951/stone-906.obj"},{"mesh":"arch/num_stones=951/stone-907.obj"},{"mesh":"arch/num_stones=951/stone-908.obj"},{"mesh":"arch/num_stones=951/stone-909.obj"},{"mesh":"arch/num_stones=951/stone-910.obj"},{"mesh":"arch/num_stones=951/stone-911.obj"},{"mesh":"arch/num_stones=951/stone-912.obj"},{"mesh":"arch/num_stones=951/stone-913.obj"},{"mesh":"arch/num_stones=951/stone-914.obj"},{"mesh":"arch/num_stones=951/stone-915.obj"},{"mesh":"arch/num_stones=951/stone-916.obj"},{"mesh":"arch/num_stones=951/stone-917.obj"},{"mesh":"arch/num_stones=951/stone-918.obj"},{"mesh":"arch/num_stones=951/stone-919.obj"},{"mesh":"arch/num_stones=951/stone-920.obj"},{"mesh":"arch/num_stones=951/stone-921.obj"},{"mesh":"arch/num_stones=951/stone-922.obj"},{"mesh":"arch/num_stones=951/stone-923.obj"},{"mesh":"arch/num_stones=951/stone-924.obj"},{"mesh":"arch/num_stones=951/stone-925.obj"},{"mesh":"arch/num_stones=951/stone-926.obj"},{"mesh":"arch/num_stones=951/stone-927.obj"},{"mesh":"arch/num_stones=951/stone-928.obj"},{"mesh":"arch/num_stones=951/stone-929.obj"},{"mesh":"arch/num_stones=951/stone-930.obj"},{"mesh":"arch/num_stones=951/stone-931.obj"},{"mesh":"arch/num_stones=951/stone-932.obj"},{"mesh":"arch/num_stones=951/stone-933.obj"},{"mesh":"arch/num_stones=951/stone-934.obj"},{"mesh":"arch/num_stones=951/stone-935.obj"},{"mesh":"arch/num_stones=951/stone-936.obj"},{"mesh":"arch/num_stones=951/stone-937.obj"},{"mesh":"arch/num_stones=951/stone-938.obj"},{"mesh":"arch/num_stones=951/stone-939.obj"},{"mesh":"arch/num_stones=951/stone-940.obj"},{"mesh":"arch/num_stones=951/stone-941.obj"},{"mesh":"arch/num_stones=951/stone-942.obj"},{"mesh":"arch/num_stones=951/stone-943.obj"},{"mesh":"arch/num_stones=951/stone-944.obj"},{"mesh":"arch/num_stones=951/stone-945.obj"},{"mesh":"arch/num_stones=951/stone-946.obj"},{"mesh":"arch/num_stones=951/stone-947.obj"},{"mesh":"arch/num_stones=951/stone-948.obj"},{"mesh":"arch/num_stones=951/stone-949.obj"},{"mesh":"arch/num_stones=951/stone-950.obj"},{"mesh":"arch/num_stones=951/stone-951.obj"}]}}